llama_index/readers/gpt_repo/__init__.py
llama_index/readers/gpt_repo/base.py
llama_index_readers_gpt_repo-0.4.1.dist-info/METADATA
llama_index_readers_gpt_repo-0.4.1.dist-info/WHEEL
llama_index_readers_gpt_repo-0.4.1.dist-info/licenses/LICENSE
llama_index_readers_gpt_repo-0.4.1.dist-info/RECORD
