Metadata-Version: 2.4
Name: llama-index-readers-gpt-repo
Version: 0.4.1
Summary: llama-index readers gpt_repo integration
Author-email: Your Name <you@example.com>
Maintainer: mpoon
License-Expression: MIT
License-File: LICENSE
Requires-Python: <4.0,>=3.9
Requires-Dist: llama-index-core<0.15,>=0.13.0
